{"metadata":{},"options":{"assumptions":{},"compact":false,"sourceMaps":true,"ast":true,"babelrc":false,"configFile":false,"parserOpts":{"sourceType":"module","sourceFileName":"/Users/phatca/Documents/GitHub/professor-trading-card/app/packages/dev-error-overlay/client.js","plugins":["*","flow","jsx","asyncGenerators","bigInt","classPrivateMethods","classPrivateProperties","classProperties","doExpressions","dynamicImport","exportDefaultFrom","exportExtensions","exportNamespaceFrom","functionBind","functionSent","importMeta","nullishCoalescingOperator","numericSeparator","objectRestSpread","optionalCatchBinding","optionalChaining",["pipelineOperator",{"proposal":"minimal"}],"throwExpressions","classProperties","classPrivateProperties","jsx","nullishCoalescingOperator","nullishCoalescingOperator","optionalChaining","optionalChaining","optionalCatchBinding","optionalCatchBinding","classProperties","classPrivateProperties","classPrivateMethods","classProperties","classPrivateProperties","asyncGenerators","asyncGenerators","objectRestSpread","objectRestSpread","logicalAssignment"],"allowImportExportEverywhere":true,"allowReturnOutsideFunction":true,"allowUndeclaredExports":true,"strictMode":false},"caller":{"name":"meteor","arch":"web.browser"},"sourceFileName":"packages/dev-error-overlay/client.js","filename":"/Users/phatca/Documents/GitHub/professor-trading-card/app/packages/dev-error-overlay/client.js","targets":{},"cloneInputAst":true,"browserslistConfigFile":false,"passPerPreset":false,"envName":"development","cwd":"/Users/phatca/Documents/GitHub/professor-trading-card/app","root":"/Users/phatca/Documents/GitHub/professor-trading-card/app","rootMode":"root","plugins":[{"key":"base$0","visitor":{"_exploded":true,"_verified":true},"options":{},"externalDependencies":[]},{"key":"base$0$0","visitor":{"Program":{"enter":[null],"exit":[null]},"_exploded":true,"_verified":true},"options":{"avoidModernSyntax":false,"enforceStrictMode":false,"dynamicImport":true,"generateLetDeclarations":true},"externalDependencies":[]},{"key":"transform-runtime","visitor":{"MemberExpression":{"enter":[null]},"ObjectPattern":{"enter":[null]},"BinaryExpression":{"enter":[null]},"Identifier":{"enter":[null]},"JSXIdentifier":{"enter":[null]},"_exploded":true,"_verified":true},"options":{"version":"7.17.2","helpers":true,"useESModules":false,"corejs":false},"externalDependencies":[]},{"key":"proposal-class-properties","visitor":{"ExportDefaultDeclaration":{"enter":[null]},"_exploded":true,"_verified":true,"ClassExpression":{"enter":[null]},"ClassDeclaration":{"enter":[null]}},"options":{"loose":true},"externalDependencies":[]},{"key":"transform-react-jsx","visitor":{"JSXNamespacedName":{"enter":[null]},"JSXSpreadChild":{"enter":[null]},"Program":{"enter":[null]},"JSXFragment":{"exit":[null]},"JSXElement":{"exit":[null]},"JSXAttribute":{"enter":[null]},"_exploded":true,"_verified":true},"options":{"pragma":"React.createElement","pragmaFrag":"React.Fragment","runtime":"classic","throwIfNamespace":true,"useBuiltIns":false},"externalDependencies":[]},{"key":"transform-react-display-name","visitor":{"ExportDefaultDeclaration":{"enter":[null]},"CallExpression":{"enter":[null]},"_exploded":true,"_verified":true},"options":{},"externalDependencies":[]},{"key":"transform-react-pure-annotations","visitor":{"CallExpression":{"enter":[null]},"_exploded":true,"_verified":true},"options":{},"externalDependencies":[]},{"key":"syntax-nullish-coalescing-operator","visitor":{"_exploded":true,"_verified":true},"options":{},"externalDependencies":[]},{"key":"proposal-nullish-coalescing-operator","visitor":{"LogicalExpression":{"enter":[null]},"_exploded":true,"_verified":true},"options":{},"externalDependencies":[]},{"key":"syntax-optional-chaining","visitor":{"_exploded":true,"_verified":true},"options":{},"externalDependencies":[]},{"key":"proposal-optional-chaining","visitor":{"OptionalCallExpression":{"enter":[null]},"OptionalMemberExpression":{"enter":[null]},"_exploded":true,"_verified":true},"options":{},"externalDependencies":[]},{"key":"syntax-optional-catch-binding","visitor":{"_exploded":true,"_verified":true},"options":{},"externalDependencies":[]},{"key":"proposal-optional-catch-binding","visitor":{"CatchClause":{"enter":[null]},"_exploded":true,"_verified":true},"options":{},"externalDependencies":[]},{"key":"syntax-class-properties","visitor":{"_exploded":true,"_verified":true},"options":{},"externalDependencies":[]},{"key":"proposal-class-properties","visitor":{"ExportDefaultDeclaration":{"enter":[null]},"_exploded":true,"_verified":true,"ClassExpression":{"enter":[null]},"ClassDeclaration":{"enter":[null]}},"options":{},"externalDependencies":[]},{"key":"syntax-async-generators","visitor":{"_exploded":true,"_verified":true},"options":{},"externalDependencies":[]},{"key":"proposal-async-generator-functions","visitor":{"Program":{"enter":[null]},"_exploded":true,"_verified":true},"options":{},"externalDependencies":[]},{"key":"syntax-object-rest-spread","visitor":{"_exploded":true,"_verified":true},"options":{},"externalDependencies":[]},{"key":"proposal-object-rest-spread","visitor":{"VariableDeclarator":{"enter":[null]},"ExportNamedDeclaration":{"enter":[null]},"CatchClause":{"enter":[null]},"AssignmentExpression":{"enter":[null]},"ArrayPattern":{"enter":[null]},"ObjectExpression":{"enter":[null]},"FunctionDeclaration":{"enter":[null]},"FunctionExpression":{"enter":[null]},"ObjectMethod":{"enter":[null]},"ArrowFunctionExpression":{"enter":[null]},"ClassMethod":{"enter":[null]},"ClassPrivateMethod":{"enter":[null]},"ForInStatement":{"enter":[null]},"ForOfStatement":{"enter":[null]},"_exploded":true,"_verified":true},"options":{},"externalDependencies":[]},{"key":"proposal-logical-assignment-operators","visitor":{"AssignmentExpression":{"enter":[null]},"_exploded":true,"_verified":true},"options":{},"externalDependencies":[]},{"key":"transform-literals","visitor":{"NumericLiteral":{"enter":[null]},"StringLiteral":{"enter":[null]},"_exploded":true,"_verified":true},"options":{},"externalDependencies":[]},{"key":"transform-template-literals","visitor":{"TaggedTemplateExpression":{"enter":[null]},"TemplateLiteral":{"enter":[null]},"_exploded":true,"_verified":true},"options":{},"externalDependencies":[]},{"key":"transform-parameters","visitor":{"_exploded":true,"_verified":true,"FunctionDeclaration":{"enter":[null]},"FunctionExpression":{"enter":[null]},"ObjectMethod":{"enter":[null]},"ArrowFunctionExpression":{"enter":[null]},"ClassMethod":{"enter":[null]},"ClassPrivateMethod":{"enter":[null]}},"options":{},"externalDependencies":[]},{"key":"transform-exponentiation-operator","visitor":{"AssignmentExpression":{"enter":[null]},"BinaryExpression":{"enter":[null]},"_exploded":true,"_verified":true},"options":{},"externalDependencies":[]}],"presets":[],"generatorOpts":{"filename":"/Users/phatca/Documents/GitHub/professor-trading-card/app/packages/dev-error-overlay/client.js","comments":true,"compact":false,"sourceMaps":true,"sourceFileName":"packages/dev-error-overlay/client.js"}},"code":"const styles = \"\\n  .container {\\n    all: initial;\\n    background: #FEFEFE;\\n    padding: 50px;\\n    min-height: 30vh;\\n    max-height: 100%;\\n    width: 100%;\\n    position: fixed;\\n    left: 0;\\n    top: 0;\\n    font-family: sans-serif;\\n    box-shadow: inset 0 0 100px #e411111f, 0 0 20px #00000085;\\n    box-sizing: border-box;\\n    overflow-y: auto;\\n    z-index: 1000000;\\n  }\\n\\n  .section {\\n    margin-bottom: 50px;\\n  }\\n\\n  pre {\\n    overflow-x: auto;\\n  }\\n\";\nfunction createSection(title, content) {\n  var sectionContainer = document.createElement('div');\n  sectionContainer.classList.add('section');\n  var header = document.createElement('h3');\n  header.textContent = title;\n  sectionContainer.appendChild(header);\n  var message = document.createElement('pre');\n  message.innerHTML = content;\n  sectionContainer.appendChild(message);\n  return sectionContainer;\n}\nlet container = null;\nlet contentEl = null;\nfunction init() {\n  if (container) {\n    return;\n  }\n  container = document.createElement('div');\n  document.body.append(container);\n  contentEl = document.createElement('div');\n  contentEl.classList.add('container');\n  let shadow = container.attachShadow({\n    mode: 'open'\n  });\n  shadow.appendChild(contentEl);\n  let style = document.createElement('style');\n  style.textContent = styles;\n  shadow.appendChild(style);\n  let button = document.createElement('button');\n  button.textContent = 'Close';\n  button.addEventListener('click', close);\n  contentEl.appendChild(button);\n}\nfunction close() {\n  document.body.removeChild(container);\n  container = null;\n  contentEl = null;\n}\nDevErrorOverlay = {\n  showMessage(title, message) {\n    init();\n    let sectionEl = createSection(title, message);\n    contentEl.prepend(sectionEl);\n    return () => {\n      if (container && contentEl && sectionEl.parentNode === contentEl) {\n        contentEl.removeChild(sectionEl);\n        if (contentEl.childNodes.length === 1) {\n          close();\n        }\n      }\n    };\n  }\n};","map":{"version":3,"names":["styles","createSection","title","content","sectionContainer","document","createElement","classList","add","header","textContent","appendChild","message","innerHTML","container","contentEl","init","body","append","shadow","attachShadow","mode","style","button","addEventListener","close","removeChild","DevErrorOverlay","showMessage","sectionEl","prepend","parentNode","childNodes","length"],"sources":["packages/dev-error-overlay/client.js"],"sourcesContent":["const styles = `\n  .container {\n    all: initial;\n    background: #FEFEFE;\n    padding: 50px;\n    min-height: 30vh;\n    max-height: 100%;\n    width: 100%;\n    position: fixed;\n    left: 0;\n    top: 0;\n    font-family: sans-serif;\n    box-shadow: inset 0 0 100px #e411111f, 0 0 20px #00000085;\n    box-sizing: border-box;\n    overflow-y: auto;\n    z-index: 1000000;\n  }\n\n  .section {\n    margin-bottom: 50px;\n  }\n\n  pre {\n    overflow-x: auto;\n  }\n`;\n\nfunction createSection (title, content) {\n  var sectionContainer = document.createElement('div');\n  sectionContainer.classList.add('section');\n\n  var header = document.createElement('h3');\n  header.textContent = title;\n  sectionContainer.appendChild(header);\n\n  var message = document.createElement('pre');\n  message.innerHTML = content;\n  sectionContainer.appendChild(message);\n\n  return sectionContainer;\n}\n\nlet container = null;\nlet contentEl = null;\n\nfunction init () {\n  if (container) {\n    return;\n  }\n\n  container = document.createElement('div');\n  document.body.append(container);\n\n  contentEl = document.createElement('div');\n  contentEl.classList.add('container');\n\n  let shadow = container.attachShadow({ mode: 'open' });\n  shadow.appendChild(contentEl);\n\n  let style = document.createElement('style');\n  style.textContent = styles;\n  shadow.appendChild(style);\n\n  let button = document.createElement('button');\n  button.textContent = 'Close';\n  button.addEventListener('click', close);\n  contentEl.appendChild(button);\n}\n\nfunction close() {\n  document.body.removeChild(container);\n  container = null;\n  contentEl = null;\n}\n\nDevErrorOverlay = {\n  showMessage(title, message) {\n    init();\n\n    let sectionEl = createSection(title, message);\n    contentEl.prepend(sectionEl);\n\n    return () => {\n      if (container && contentEl && sectionEl.parentNode === contentEl) {\n        contentEl.removeChild(sectionEl);\n\n        if (contentEl.childNodes.length === 1) {\n          close();\n        }\n      }\n    };\n  }\n}\n"],"mappings":"AAAA,MAAMA,MAAM,6cAyBX;AAED,SAASC,aAAaA,CAAEC,KAAK,EAAEC,OAAO,EAAE;EACtC,IAAIC,gBAAgB,GAAGC,QAAQ,CAACC,aAAa,CAAC,KAAK,CAAC;EACpDF,gBAAgB,CAACG,SAAS,CAACC,GAAG,CAAC,SAAS,CAAC;EAEzC,IAAIC,MAAM,GAAGJ,QAAQ,CAACC,aAAa,CAAC,IAAI,CAAC;EACzCG,MAAM,CAACC,WAAW,GAAGR,KAAK;EAC1BE,gBAAgB,CAACO,WAAW,CAACF,MAAM,CAAC;EAEpC,IAAIG,OAAO,GAAGP,QAAQ,CAACC,aAAa,CAAC,KAAK,CAAC;EAC3CM,OAAO,CAACC,SAAS,GAAGV,OAAO;EAC3BC,gBAAgB,CAACO,WAAW,CAACC,OAAO,CAAC;EAErC,OAAOR,gBAAgB;AACzB;AAEA,IAAIU,SAAS,GAAG,IAAI;AACpB,IAAIC,SAAS,GAAG,IAAI;AAEpB,SAASC,IAAIA,CAAA,EAAI;EACf,IAAIF,SAAS,EAAE;IACb;EACF;EAEAA,SAAS,GAAGT,QAAQ,CAACC,aAAa,CAAC,KAAK,CAAC;EACzCD,QAAQ,CAACY,IAAI,CAACC,MAAM,CAACJ,SAAS,CAAC;EAE/BC,SAAS,GAAGV,QAAQ,CAACC,aAAa,CAAC,KAAK,CAAC;EACzCS,SAAS,CAACR,SAAS,CAACC,GAAG,CAAC,WAAW,CAAC;EAEpC,IAAIW,MAAM,GAAGL,SAAS,CAACM,YAAY,CAAC;IAAEC,IAAI,EAAE;EAAO,CAAC,CAAC;EACrDF,MAAM,CAACR,WAAW,CAACI,SAAS,CAAC;EAE7B,IAAIO,KAAK,GAAGjB,QAAQ,CAACC,aAAa,CAAC,OAAO,CAAC;EAC3CgB,KAAK,CAACZ,WAAW,GAAGV,MAAM;EAC1BmB,MAAM,CAACR,WAAW,CAACW,KAAK,CAAC;EAEzB,IAAIC,MAAM,GAAGlB,QAAQ,CAACC,aAAa,CAAC,QAAQ,CAAC;EAC7CiB,MAAM,CAACb,WAAW,GAAG,OAAO;EAC5Ba,MAAM,CAACC,gBAAgB,CAAC,OAAO,EAAEC,KAAK,CAAC;EACvCV,SAAS,CAACJ,WAAW,CAACY,MAAM,CAAC;AAC/B;AAEA,SAASE,KAAKA,CAAA,EAAG;EACfpB,QAAQ,CAACY,IAAI,CAACS,WAAW,CAACZ,SAAS,CAAC;EACpCA,SAAS,GAAG,IAAI;EAChBC,SAAS,GAAG,IAAI;AAClB;AAEAY,eAAe,GAAG;EAChBC,WAAWA,CAAC1B,KAAK,EAAEU,OAAO,EAAE;IAC1BI,IAAI,CAAC,CAAC;IAEN,IAAIa,SAAS,GAAG5B,aAAa,CAACC,KAAK,EAAEU,OAAO,CAAC;IAC7CG,SAAS,CAACe,OAAO,CAACD,SAAS,CAAC;IAE5B,OAAO,MAAM;MACX,IAAIf,SAAS,IAAIC,SAAS,IAAIc,SAAS,CAACE,UAAU,KAAKhB,SAAS,EAAE;QAChEA,SAAS,CAACW,WAAW,CAACG,SAAS,CAAC;QAEhC,IAAId,SAAS,CAACiB,UAAU,CAACC,MAAM,KAAK,CAAC,EAAE;UACrCR,KAAK,CAAC,CAAC;QACT;MACF;IACF,CAAC;EACH;AACF,CAAC"},"sourceType":"module","externalDependencies":{},"hash":"3704382bff08cf13dd7a190c8adb98327c713bf1"}
